{"updated": 1609113070.1618288, "source": "https://big.one/cn/activity/defi", "title": "Big.One - DeFi \u6316\u77ff\u6c60", "items": [{"title": "DrEE \u77ff\u6c60", "url": "https://big.one/cn/coffer/pos/68", "\u6316\u77ff\u5e01\u79cd": "DrEE", "\u6700\u5c0f\u8d77\u6295\u91d1\u989d": "100", "\u52df\u96c6\u8fdb\u5ea6": 97.0, "\u6295\u8d44\u5468\u671f": "60\u5929", "\u6536\u76ca\u5e01\u79cd": "DrEE"}, {"title": "Eth2 \u9a8c\u8bc1\u4eba\u8282\u70b9\u77ff\u6c60", "url": "https://big.one/cn/coffer/pos/66", "\u6316\u77ff\u5e01\u79cd": "ETH", "\u6700\u5c0f\u8d77\u6295\u91d1\u989d": "0.1", "\u52df\u96c6\u8fdb\u5ea6": 71.1, "\u6295\u8d44\u5468\u671f": "Eth2 \u9a8c\u8bc1\u4eba\u8282\u70b9", "\u6536\u76ca\u5e01\u79cd": "ETH"}, {"title": "EOS DFS(\u5927\u4e30\u6536) \u673a\u67aa\u6c60", "url": "https://big.one/cn/coffer/pos/65", "\u6316\u77ff\u5e01\u79cd": "EOS", "\u6700\u5c0f\u8d77\u6295\u91d1\u989d": "10", "\u52df\u96c6\u8fdb\u5ea6": 85.4, "\u6295\u8d44\u5468\u671f": "EOS \u5927\u4e30\u6536\u6316\u77ff", "\u6536\u76ca\u5e01\u79cd": "EOS"}, {"title": "BTC DeFi \u673a\u67aa\u6c60", "url": "https://big.one/cn/coffer/pos/54", "\u6316\u77ff\u5e01\u79cd": "BTC", "\u6700\u5c0f\u8d77\u6295\u91d1\u989d": "0.01", "\u52df\u96c6\u8fdb\u5ea6": 52.5, "\u6295\u8d44\u5468\u671f": "BTC \u673a\u67aa\u6c60\u6d3b\u671f", "\u6536\u76ca\u5e01\u79cd": "BTC"}, {"title": "EOS \u5b9a\u671f\u77ff\u6c60", "url": "https://big.one/cn/coffer/pos/29", "\u6316\u77ff\u5e01\u79cd": "EOS", "\u6700\u5c0f\u8d77\u6295\u91d1\u989d": "10", "\u52df\u96c6\u8fdb\u5ea6": 85.5, "\u6295\u8d44\u5468\u671f": "180\u5929", "\u6536\u76ca\u5e01\u79cd": "EOS"}, {"title": "GXChain", "url": "https://big.one/cn/coffer/pos/2", "\u6316\u77ff\u5e01\u79cd": "GXC", "\u6700\u5c0f\u8d77\u6295\u91d1\u989d": "20", "\u52df\u96c6\u8fdb\u5ea6": 1.8, "\u6295\u8d44\u5468\u671f": "\u6d3b\u671f", "\u6536\u76ca\u5e01\u79cd": "GXC"}, {"title": "GXChain", "url": "https://big.one/cn/coffer/pos/2", "\u6316\u77ff\u5e01\u79cd": "GXC", "\u6700\u5c0f\u8d77\u6295\u91d1\u989d": "20", "\u52df\u96c6\u8fdb\u5ea6": 12.2, "\u6295\u8d44\u5468\u671f": "30\u5929", "\u6536\u76ca\u5e01\u79cd": "GXC"}, {"title": "GXChain", "url": "https://big.one/cn/coffer/pos/2", "\u6316\u77ff\u5e01\u79cd": "GXC", "\u6700\u5c0f\u8d77\u6295\u91d1\u989d": "20", "\u52df\u96c6\u8fdb\u5ea6": 20.0, "\u6295\u8d44\u5468\u671f": "90\u5929", "\u6536\u76ca\u5e01\u79cd": "GXC"}, {"title": "GXChain", "url": "https://big.one/cn/coffer/pos/2", "\u6316\u77ff\u5e01\u79cd": "GXC", "\u6700\u5c0f\u8d77\u6295\u91d1\u989d": "20", "\u52df\u96c6\u8fdb\u5ea6": 46.2, "\u6295\u8d44\u5468\u671f": "180\u5929", "\u6536\u76ca\u5e01\u79cd": "GXC"}, {"title": "BTC \u673a\u67aa\u6c60 2(\u539fCurve\u77ff\u6c60)", "url": "https://big.one/cn/coffer/pos/49", "\u6316\u77ff\u5e01\u79cd": "BTC", "\u6700\u5c0f\u8d77\u6295\u91d1\u989d": "0.01", "\u52df\u96c6\u8fdb\u5ea6": 30.9, "\u6295\u8d44\u5468\u671f": "BTC \u673a\u67aa\u6c60 2 \u6316\u77ff\u6d3b\u671f", "\u6536\u76ca\u5e01\u79cd": "BTC"}, {"title": "ANG \u77ff\u6c60", "url": "https://big.one/cn/coffer/pos/28", "\u6316\u77ff\u5e01\u79cd": "ANG", "\u6700\u5c0f\u8d77\u6295\u91d1\u989d": "500", "\u52df\u96c6\u8fdb\u5ea6": 100.0, "\u6295\u8d44\u5468\u671f": "90\u5929", "\u6536\u76ca\u5e01\u79cd": "ANG"}, {"title": "ANG \u77ff\u6c60", "url": "https://big.one/cn/coffer/pos/28", "\u6316\u77ff\u5e01\u79cd": "ANG", "\u6700\u5c0f\u8d77\u6295\u91d1\u989d": "500", "\u52df\u96c6\u8fdb\u5ea6": 100.0, "\u6295\u8d44\u5468\u671f": "180\u5929", "\u6536\u76ca\u5e01\u79cd": "ANG"}, {"title": "ANG \u77ff\u6c60", "url": "https://big.one/cn/coffer/pos/28", "\u6316\u77ff\u5e01\u79cd": "ANG", "\u6700\u5c0f\u8d77\u6295\u91d1\u989d": "500", "\u52df\u96c6\u8fdb\u5ea6": 100.0, "\u6295\u8d44\u5468\u671f": "360\u5929", "\u6536\u76ca\u5e01\u79cd": "ANG"}, {"title": "EOS", "url": "https://big.one/cn/coffer/pos/4", "\u6316\u77ff\u5e01\u79cd": "EOS", "\u6700\u5c0f\u8d77\u6295\u91d1\u989d": "10", "\u52df\u96c6\u8fdb\u5ea6": 0.0, "\u6295\u8d44\u5468\u671f": "\u6d3b\u671f", "\u6536\u76ca\u5e01\u79cd": "EOS"}, {"title": "EOS", "url": "https://big.one/cn/coffer/pos/4", "\u6316\u77ff\u5e01\u79cd": "EOS", "\u6700\u5c0f\u8d77\u6295\u91d1\u989d": "10", "\u52df\u96c6\u8fdb\u5ea6": 0.2, "\u6295\u8d44\u5468\u671f": "30\u5929", "\u6536\u76ca\u5e01\u79cd": "EOS"}, {"title": "EOS", "url": "https://big.one/cn/coffer/pos/4", "\u6316\u77ff\u5e01\u79cd": "EOS", "\u6700\u5c0f\u8d77\u6295\u91d1\u989d": "10", "\u52df\u96c6\u8fdb\u5ea6": 0.1, "\u6295\u8d44\u5468\u671f": "90\u5929", "\u6536\u76ca\u5e01\u79cd": "EOS"}, {"title": "EOS", "url": "https://big.one/cn/coffer/pos/4", "\u6316\u77ff\u5e01\u79cd": "EOS", "\u6700\u5c0f\u8d77\u6295\u91d1\u989d": "10", "\u52df\u96c6\u8fdb\u5ea6": 1.5, "\u6295\u8d44\u5468\u671f": "180\u5929", "\u6536\u76ca\u5e01\u79cd": "EOS"}, {"title": "ETH DeFi \u5b87\u5b99\u6700\u5f3a\u673a\u67aa\u6c60", "url": "https://big.one/cn/coffer/pos/46", "\u6316\u77ff\u5e01\u79cd": "ETH", "\u6700\u5c0f\u8d77\u6295\u91d1\u989d": "0.1", "\u52df\u96c6\u8fdb\u5ea6": 18.8, "\u6295\u8d44\u5468\u671f": "ETH \u5b87\u5b99\u6700\u5f3a\u673a\u67aa\u6c60\u6d3b\u671f", "\u6536\u76ca\u5e01\u79cd": "USDT"}, {"title": "DOT\uff08Polkadot\uff09\u77ff\u6c60", "url": "https://big.one/cn/coffer/pos/42", "\u6316\u77ff\u5e01\u79cd": "DOT", "\u6700\u5c0f\u8d77\u6295\u91d1\u989d": "1", "\u52df\u96c6\u8fdb\u5ea6": 13.0, "\u6295\u8d44\u5468\u671f": "DOT \u6d3b\u671f", "\u6536\u76ca\u5e01\u79cd": "DOT"}, {"title": "BIUT \u53cc\u6316\u77ff\u6c60", "url": "https://big.one/cn/coffer/pos/13", "\u6316\u77ff\u5e01\u79cd": "BIUT", "\u6700\u5c0f\u8d77\u6295\u91d1\u989d": "1000", "\u52df\u96c6\u8fdb\u5ea6": 92.8, "\u6295\u8d44\u5468\u671f": "125\u5929", "\u6536\u76ca\u5e01\u79cd": "BIUT"}, {"title": "BIUT \u53cc\u6316\u77ff\u6c60", "url": "https://big.one/cn/coffer/pos/13", "\u6316\u77ff\u5e01\u79cd": "BIUT", "\u6700\u5c0f\u8d77\u6295\u91d1\u989d": "1000", "\u52df\u96c6\u8fdb\u5ea6": 85.1, "\u6295\u8d44\u5468\u671f": "180\u5929", "\u6536\u76ca\u5e01\u79cd": "BIUT"}, {"title": "Nucypher \u9501\u4ed3\u6316\u77ff", "url": "https://big.one/cn/coffer/pos/63", "\u6316\u77ff\u5e01\u79cd": "ETH", "\u6700\u5c0f\u8d77\u6295\u91d1\u989d": "0.1", "\u52df\u96c6\u8fdb\u5ea6": 100.0, "\u6295\u8d44\u5468\u671f": "ETH \u9501\u4ed3\u6316\u77ff 180\u5929", "\u6536\u76ca\u5e01\u79cd": "NU"}, {"title": "USDT DeFi \u5b87\u5b99\u6700\u5f3a\u673a\u67aa\u6c60", "url": "https://big.one/cn/coffer/pos/43", "\u6316\u77ff\u5e01\u79cd": "USDT", "\u6700\u5c0f\u8d77\u6295\u91d1\u989d": "100", "\u52df\u96c6\u8fdb\u5ea6": 3.0, "\u6295\u8d44\u5468\u671f": "USDT \u5b87\u5b99\u6700\u5f3a\u673a\u67aa\u6c60\u6d3b\u671f", "\u6536\u76ca\u5e01\u79cd": "USDT"}, {"title": "CPS \u77ff\u6c60", "url": "https://big.one/cn/coffer/pos/26", "\u6316\u77ff\u5e01\u79cd": "CPS", "\u6700\u5c0f\u8d77\u6295\u91d1\u989d": "1000", "\u52df\u96c6\u8fdb\u5ea6": 100.0, "\u6295\u8d44\u5468\u671f": "180\u5929", "\u6536\u76ca\u5e01\u79cd": "CPS"}, {"title": "USDC DeFi \u673a\u67aa\u6c60", "url": "https://big.one/cn/coffer/pos/56", "\u6316\u77ff\u5e01\u79cd": "USDC", "\u6700\u5c0f\u8d77\u6295\u91d1\u989d": "100", "\u52df\u96c6\u8fdb\u5ea6": 0.1, "\u6295\u8d44\u5468\u671f": "USDC \u673a\u67aa\u6c60\u6d3b\u671f", "\u6536\u76ca\u5e01\u79cd": "USDT"}, {"title": "QTUM", "url": "https://big.one/cn/coffer/pos/5", "\u6316\u77ff\u5e01\u79cd": "QTUM", "\u6700\u5c0f\u8d77\u6295\u91d1\u989d": "10", "\u52df\u96c6\u8fdb\u5ea6": 0.7, "\u6295\u8d44\u5468\u671f": "\u6d3b\u671f", "\u6536\u76ca\u5e01\u79cd": "QTUM"}, {"title": "QTUM", "url": "https://big.one/cn/coffer/pos/5", "\u6316\u77ff\u5e01\u79cd": "QTUM", "\u6700\u5c0f\u8d77\u6295\u91d1\u989d": "10", "\u52df\u96c6\u8fdb\u5ea6": 11.1, "\u6295\u8d44\u5468\u671f": "30\u5929", "\u6536\u76ca\u5e01\u79cd": "QTUM"}, {"title": "QTUM", "url": "https://big.one/cn/coffer/pos/5", "\u6316\u77ff\u5e01\u79cd": "QTUM", "\u6700\u5c0f\u8d77\u6295\u91d1\u989d": "10", "\u52df\u96c6\u8fdb\u5ea6": 9.8, "\u6295\u8d44\u5468\u671f": "90\u5929", "\u6536\u76ca\u5e01\u79cd": "QTUM"}, {"title": "QTUM", "url": "https://big.one/cn/coffer/pos/5", "\u6316\u77ff\u5e01\u79cd": "QTUM", "\u6700\u5c0f\u8d77\u6295\u91d1\u989d": "10", "\u52df\u96c6\u8fdb\u5ea6": 48.1, "\u6295\u8d44\u5468\u671f": "180\u5929", "\u6536\u76ca\u5e01\u79cd": "QTUM"}, {"title": "ONE \u548c\u8c10\u53f7-\u8001\u94c1\u4e13\u5217", "url": "https://big.one/cn/coffer/pos/51", "\u6316\u77ff\u5e01\u79cd": "ONE", "\u6700\u5c0f\u8d77\u6295\u91d1\u989d": "10000", "\u52df\u96c6\u8fdb\u5ea6": 100.0, "\u6295\u8d44\u5468\u671f": "ONE \u8001\u94c1\u4e13\u5217\u6d3b\u671f", "\u6536\u76ca\u5e01\u79cd": "ONE"}, {"title": "TRX DeFi \u673a\u67aa\u6c60", "url": "https://big.one/cn/coffer/pos/45", "\u6316\u77ff\u5e01\u79cd": "TRX", "\u6700\u5c0f\u8d77\u6295\u91d1\u989d": "1000", "\u52df\u96c6\u8fdb\u5ea6": 15.5, "\u6295\u8d44\u5468\u671f": "TRX \u673a\u67aa\u6c60\u6d3b\u671f", "\u6536\u76ca\u5e01\u79cd": "USDT"}, {"title": "\u6ce2\u5361\u751f\u6001 Plasm \u77ff\u6c60", "url": "https://big.one/cn/coffer/pos/44", "\u6316\u77ff\u5e01\u79cd": "ETH", "\u6700\u5c0f\u8d77\u6295\u91d1\u989d": "0.1", "\u52df\u96c6\u8fdb\u5ea6": 100.0, "\u6295\u8d44\u5468\u671f": "30\u5929", "\u6536\u76ca\u5e01\u79cd": "PLM"}, {"title": "\u6ce2\u5361\u751f\u6001 Plasm \u77ff\u6c60", "url": "https://big.one/cn/coffer/pos/44", "\u6316\u77ff\u5e01\u79cd": "ETH", "\u6700\u5c0f\u8d77\u6295\u91d1\u989d": "0.1", "\u52df\u96c6\u8fdb\u5ea6": 100.0, "\u6295\u8d44\u5468\u671f": "100\u5929", "\u6536\u76ca\u5e01\u79cd": "PLM"}]}